ml_swissknife/__init__.py
ml_swissknife/anthropic_utils.py
ml_swissknife/blocks.py
ml_swissknife/db_utils.py
ml_swissknife/db_utils_sqlite.py
ml_swissknife/distributed_utils.py
ml_swissknife/numerical.py
ml_swissknife/numerical_distributed.py
ml_swissknife/openai_utils.py
ml_swissknife/types.py
ml_swissknife/utils.py
ml_swissknife/wrapper.py
ml_swissknife-0.1.30.dist-info/LICENSE
ml_swissknife-0.1.30.dist-info/METADATA
ml_swissknife-0.1.30.dist-info/WHEEL
ml_swissknife-0.1.30.dist-info/top_level.txt
ml_swissknife-0.1.30.dist-info/RECORD
