Metadata-Version: 2.1
Name: ml-swissknife
Version: 0.1.30
Summary: Reusable ML research primitives for fast prototyping.
Home-page: https://github.com/lxuechen/ml-swissknife
Author: Xuechen Li, Yann Dubois, Tianyi Zhang
Author-email: lxuechen@cs.toronto.edu, yanndubs@stanford.edu, tz58@stanford.edu
License: MIT
Classifier: Programming Language :: Python :: 3
Classifier: License :: OSI Approved :: Apache Software License
Requires-Python: ~=3.7
License-File: LICENSE
Requires-Dist: torch
Requires-Dist: torchvision
Requires-Dist: tqdm
Requires-Dist: numpy
Requires-Dist: scipy
Requires-Dist: gputil
Requires-Dist: fire
Requires-Dist: requests
Requires-Dist: nltk
Requires-Dist: transformers
Requires-Dist: datasets
Requires-Dist: gdown >=4.4.0
Requires-Dist: pandas >=2.0.0
Requires-Dist: pytest
Requires-Dist: matplotlib
Requires-Dist: seaborn
Requires-Dist: imageio
Requires-Dist: wandb
Requires-Dist: openai >=0.27.2
Requires-Dist: sqlalchemy >=2.0.0
Provides-Extra: full
Requires-Dist: bibtexparser ; extra == 'full'
Requires-Dist: spacy ; extra == 'full'
Requires-Dist: crfm-helm ; extra == 'full'
Requires-Dist: numba ; extra == 'full'
Requires-Dist: cvxpy ; extra == 'full'
Provides-Extra: latex
Requires-Dist: bibtexparser ; extra == 'latex'
